simple_blast/__init__.py
simple_blast/blast_command.py
simple_blast/blastdb.py
simple_blast/blastdb_cache.py
simple_blast/blasting.py
simple_blast/convert.py
simple_blast/fifo.py
simple_blast/multiformat.py
simple_blast/sam.py
simple_blast/seqs.py
simple_blast-0.7.5.dist-info/licenses/LICENSE
simple_blast-0.7.5.dist-info/METADATA
simple_blast-0.7.5.dist-info/WHEEL
simple_blast-0.7.5.dist-info/top_level.txt
simple_blast-0.7.5.dist-info/RECORD
