Metadata-Version: 2.4
Name: simple_blast
Version: 0.7.5
Summary: A simple library for executing BLAST searches with ncbi-blast+
Author-email: Andrew Tapia <andrew.tapia@uky.edu>
License-Expression: MIT
Project-URL: Homepage, https://github.com/actapia/simple_blast
Project-URL: Bug Tracker, https://github.com/actapia/simple_blast
Requires-Python: >=3.11
License-File: LICENSE
Requires-Dist: pandas>=1.5.3
Requires-Dist: dateparser>=1.2.0
Dynamic: license-file
